raspi_components/__init__.py
raspi_components/ADC/ADC.py
raspi_components/ADC/ADC_errors.py
raspi_components/ADC/__init__.py
raspi_components/ADC/test_ADC.py
raspi_components/button/__init__.py
raspi_components/button/button.py
raspi_components/button/button_errors.py
raspi_components/button/test_button.py
raspi_components/buzzer/__init__.py
raspi_components/buzzer/buzzer.py
raspi_components/buzzer/buzzer_errors.py
raspi_components/buzzer/test_buzzer.py
raspi_components/joystick/__init__.py
raspi_components/joystick/joystick.py
raspi_components/joystick/joystick_errors.py
raspi_components/joystick/test_joystick.py
raspi_components/light/__init__.py
raspi_components/light/light.py
raspi_components/light/light_errors.py
raspi_components/light/rgb_light.py
raspi_components/light/test_light.py
raspi_components/light/test_rgb.py
raspi_components/variable_resistor/__init__.py
raspi_components/variable_resistor/resistor.py
raspi_components/variable_resistor/resistor_errors.py
raspi_components/variable_resistor/test_resistor.py
raspi_components-1.3.2.dist-info/LICENSE
raspi_components-1.3.2.dist-info/METADATA
raspi_components-1.3.2.dist-info/WHEEL
raspi_components-1.3.2.dist-info/top_level.txt
raspi_components-1.3.2.dist-info/RECORD
