Metadata-Version: 2.1
Name: raspi-components
Version: 1.3.2
Summary: A python package for using certain components with the raspberry pi.
Home-page: https://github.com/builderdev212/package_tutorial
Author: builderdev212
License: MIT
Keywords: raspberry pi
Platform: UNKNOWN
Classifier: Programming Language :: Python :: 3
Classifier: Development Status :: 3 - Alpha
Classifier: Intended Audience :: Developers
Classifier: Natural Language :: English
Classifier: License :: OSI Approved :: MIT License
Classifier: Operating System :: OS Independent
Requires-Python: >=3
License-File: LICENSE
